README.md
emdy/.DS_Store
emdy/LICENSE.md
emdy/__init__.py
emdy/emdy.py
emdy/licenses/.DS_Store
emdy/licenses/Creative-Commons-Markdown/.DS_Store
emdy/licenses/Creative-Commons-Markdown/.git
emdy/licenses/Creative-Commons-Markdown/.github/workflows/default.yml
emdy/licenses/Creative-Commons-Markdown/.gitignore
emdy/licenses/Creative-Commons-Markdown/.npmignore
emdy/licenses/Creative-Commons-Markdown/1.0/by-nc-nd.markdown
emdy/licenses/Creative-Commons-Markdown/1.0/by-nc-sa.markdown
emdy/licenses/Creative-Commons-Markdown/1.0/by-nc.markdown
emdy/licenses/Creative-Commons-Markdown/1.0/by-nd.markdown
emdy/licenses/Creative-Commons-Markdown/1.0/by-sa.markdown
emdy/licenses/Creative-Commons-Markdown/1.0/by.markdown
emdy/licenses/Creative-Commons-Markdown/2.0/by-nc-nd.markdown
emdy/licenses/Creative-Commons-Markdown/2.0/by-nc-sa.markdown
emdy/licenses/Creative-Commons-Markdown/2.0/by-nc.markdown
emdy/licenses/Creative-Commons-Markdown/2.0/by-nd.markdown
emdy/licenses/Creative-Commons-Markdown/2.0/by-sa.markdown
emdy/licenses/Creative-Commons-Markdown/2.0/by.markdown
emdy/licenses/Creative-Commons-Markdown/2.5/by-nc-nd.markdown
emdy/licenses/Creative-Commons-Markdown/2.5/by-nc-sa.markdown
emdy/licenses/Creative-Commons-Markdown/2.5/by-nc.markdown
emdy/licenses/Creative-Commons-Markdown/2.5/by-nd.markdown
emdy/licenses/Creative-Commons-Markdown/2.5/by-sa.markdown
emdy/licenses/Creative-Commons-Markdown/2.5/by.markdown
emdy/licenses/Creative-Commons-Markdown/3.0/by-nc-nd.markdown
emdy/licenses/Creative-Commons-Markdown/3.0/by-nc-sa.markdown
emdy/licenses/Creative-Commons-Markdown/3.0/by-nc.markdown
emdy/licenses/Creative-Commons-Markdown/3.0/by-nd.markdown
emdy/licenses/Creative-Commons-Markdown/3.0/by-sa.markdown
emdy/licenses/Creative-Commons-Markdown/3.0/by.markdown
emdy/licenses/Creative-Commons-Markdown/4.0/by-nc-nd.markdown
emdy/licenses/Creative-Commons-Markdown/4.0/by-nc-sa.markdown
emdy/licenses/Creative-Commons-Markdown/4.0/by-nc.markdown
emdy-1.0.0.dist-info/entry_points.txt
emdy-1.0.0.dist-info/LICENSE.md
emdy-1.0.0.dist-info/WHEEL
emdy-1.0.0.dist-info/METADATA
emdy-1.0.0.dist-info/RECORD
