Metadata-Version: 2.1
Name: emdy
Version: 1.0.0
Summary: Generate open source and Creative Commons licenses from your command line
Home-page: https://github.com/celsiusnarhwal/emdy
License: MIT
Keywords: license,open source,creative commons
Author: celsius narhwal
Author-email: hello@celsiusnarhwal.dev
Requires-Python: >=3.10,<4.0
Classifier: License :: OSI Approved :: MIT License
Classifier: Programming Language :: Python :: 3
Classifier: Programming Language :: Python :: 3.10
Classifier: Programming Language :: Python :: 3.11
Classifier: Topic :: Software Development :: Code Generators
Requires-Dist: click (>=8.1.3,<9.0.0)
Requires-Dist: inflect (>=6.0.2,<7.0.0)
Requires-Dist: inquirerpy (>=0.3.4,<0.4.0)
Requires-Dist: pyperclip (>=1.8.2,<2.0.0)
Project-URL: Repository, https://github.com/celsiusnarhwal/emdy
